bedrock_cgi/__init__.py
bedrock_cgi/cgi_request.py
bedrock_cgi/cgi_response.py
bedrock_cgi/constant.py
bedrock_cgi/event.py
bedrock_cgi/service_base.py
bedrock_cgi-2.0.20.dist-info/LICENSE
bedrock_cgi-2.0.20.dist-info/METADATA
bedrock_cgi-2.0.20.dist-info/WHEEL
bedrock_cgi-2.0.20.dist-info/top_level.txt
bedrock_cgi-2.0.20.dist-info/RECORD
