Metadata-Version: 2.1
Name: bedrock-cgi
Version: 2.0.20
Summary: Bedrock-2 for CGI
Home-page: https://github.com/brettonw/Bedrock-2-CGI
Author: Bretton Wade
Author-email: bretton.wade@inboundresearchmd.com
License: UNKNOWN
Project-URL: Bug Tracker, https://github.com/brettonw/Bedrock-2-CGI/issues
Platform: UNKNOWN
Classifier: Programming Language :: Python :: 3
Classifier: License :: OSI Approved :: MIT License
Classifier: Operating System :: OS Independent
Requires-Python: >=3.6
License-File: LICENSE
